tikz_python-0.0.6.dist-info/licenses/LICENSE
tikzpy/__init__.py
tikzpy/colors/__init__.py
tikzpy/colors/colors.py
tikzpy/drawing_objects/__init__.py
tikzpy/drawing_objects/arc.py
tikzpy/drawing_objects/circle.py
tikzpy/drawing_objects/drawing_object.py
tikzpy/drawing_objects/drawing_utils.py
tikzpy/drawing_objects/ellipse.py
tikzpy/drawing_objects/line.py
tikzpy/drawing_objects/node.py
tikzpy/drawing_objects/plotcoordinates.py
tikzpy/drawing_objects/point.py
tikzpy/drawing_objects/rectangle.py
tikzpy/drawing_objects/xy_plane.py
tikzpy/styles/__init__.py
tikzpy/styles/arrows_along_path.py
tikzpy/templates/tex_file.py
tikzpy/tikz_environments/__init__.py
tikzpy/tikz_environments/clip.py
tikzpy/tikz_environments/scope.py
tikzpy/tikz_environments/tikz_command.py
tikzpy/tikz_environments/tikz_environment.py
tikzpy/tikz_environments/tikz_picture.py
tikzpy/tikz_environments/tikz_style.py
tikzpy/utils/__init__.py
tikzpy/utils/helpers.py
tikzpy/utils/types.py
tikz_python-0.0.6.dist-info/METADATA
tikz_python-0.0.6.dist-info/WHEEL
tikz_python-0.0.6.dist-info/top_level.txt
tikz_python-0.0.6.dist-info/RECORD
