Metadata-Version: 2.4
Name: tikz_python
Version: 0.0.6
Summary: A python wrapper for tikz
Author-email: Luke Trujillo <ltrujillo@hmc.edu>
Project-URL: Homepage, https://github.com/ltrujello/Tikz-Python/
Project-URL: Documentation, https://ltrujello.github.io/Tikz-Python/
Classifier: Programming Language :: Python :: 3
Classifier: License :: OSI Approved :: MIT License
Classifier: Operating System :: OS Independent
Requires-Python: >=3.7
License-File: LICENSE
Dynamic: license-file
